odoo/addons/hr_holidays_team_manager/README.rst
odoo/addons/hr_holidays_team_manager/__init__.py
odoo/addons/hr_holidays_team_manager/__manifest__.py
odoo/addons/hr_holidays_team_manager/data/hr_holidays_rules.xml
odoo/addons/hr_holidays_team_manager/data/hr_holidays_security.xml
odoo/addons/hr_holidays_team_manager/i18n/hr_holidays_team_manager.pot
odoo/addons/hr_holidays_team_manager/i18n/it.po
odoo/addons/hr_holidays_team_manager/models/__init__.py
odoo/addons/hr_holidays_team_manager/models/hr_employee_base.py
odoo/addons/hr_holidays_team_manager/models/hr_leave_allocation.py
odoo/addons/hr_holidays_team_manager/readme/CONTRIBUTORS.rst
odoo/addons/hr_holidays_team_manager/readme/DESCRIPTION.rst
odoo/addons/hr_holidays_team_manager/readme/USAGE.rst
odoo/addons/hr_holidays_team_manager/static/description/icon.png
odoo/addons/hr_holidays_team_manager/static/description/index.html
odoo/addons/hr_holidays_team_manager/tests/__init__.py
odoo/addons/hr_holidays_team_manager/tests/test_hr_holidays_team_manager.py
odoo/addons/hr_holidays_team_manager/views/hr_leave_allocation_views.xml
odoo_addon_hr_holidays_team_manager-16.0.1.0.0.5.dist-info/METADATA
odoo_addon_hr_holidays_team_manager-16.0.1.0.0.5.dist-info/WHEEL
odoo_addon_hr_holidays_team_manager-16.0.1.0.0.5.dist-info/top_level.txt
odoo_addon_hr_holidays_team_manager-16.0.1.0.0.5.dist-info/RECORD
